EchoTorch-0.1.1.dist-info/DESCRIPTION.rst
EchoTorch-0.1.1.dist-info/METADATA
EchoTorch-0.1.1.dist-info/RECORD
EchoTorch-0.1.1.dist-info/WHEEL
EchoTorch-0.1.1.dist-info/metadata.json
EchoTorch-0.1.1.dist-info/top_level.txt
echotorch/__init__.py
echotorch/datasets/LogisticMapDataset.py
echotorch/datasets/MackeyGlassDataset.py
echotorch/datasets/MemTestDataset.py
echotorch/datasets/NARMADataset.py
echotorch/datasets/SwitchAttractorDataset.py
echotorch/datasets/__init__.py
echotorch/models/HNilsNet.py
echotorch/models/NilsNet.py
echotorch/models/TNilsNet.py
echotorch/models/__init__.py
echotorch/nn/BDESN.py
echotorch/nn/BDESNCell.py
echotorch/nn/BDESNPCA.py
echotorch/nn/EESN.py
echotorch/nn/ESN.py
echotorch/nn/ESN2d.py
echotorch/nn/ESNCell.py
echotorch/nn/GatedESN.py
echotorch/nn/HESN.py
echotorch/nn/ICACell.py
echotorch/nn/Identity.py
echotorch/nn/IncSFACell.py
echotorch/nn/LiESN.py
echotorch/nn/LiESNCell.py
echotorch/nn/OnlinePCACell.py
echotorch/nn/PCACell.py
echotorch/nn/RRCell.py
echotorch/nn/SFACell.py
echotorch/nn/StackedESN.py
echotorch/nn/UMESN.py
echotorch/nn/__init__.py
echotorch/transforms/__init__.py
echotorch/transforms/images/__init__.py
echotorch/transforms/text/Character.py
echotorch/transforms/text/Character2Gram.py
echotorch/transforms/text/Character3Gram.py
echotorch/transforms/text/Compose.py
echotorch/transforms/text/Embedding.py
echotorch/transforms/text/FunctionWord.py
echotorch/transforms/text/GensimModel.py
echotorch/transforms/text/GloveVector.py
echotorch/transforms/text/PartOfSpeech.py
echotorch/transforms/text/Tag.py
echotorch/transforms/text/Token.py
echotorch/transforms/text/Transformer.py
echotorch/transforms/text/__init__.py
echotorch/utils/__init__.py
echotorch/utils/error_measures.py
echotorch/utils/utility_functions.py
